<pkg-contents spec="1.12"><f n="cultibox" o="root" g="wheel" p="16877" pt="/Applications/cultibox" m="false" t="file"><f n="cultibox.app" o="root" g="wheel" p="16877"><f n="Contents" o="root" g="wheel" p="16877"><f n="Info.plist" o="root" g="wheel" p="33188"/><f n="MacOS" o="root" g="wheel" p="16877"><f n="cultibox" o="root" g="wheel" p="33261"/></f><f n="PkgInfo" o="root" g="wheel" p="33188"/><f n="Resources" o="root" g="wheel" p="16877"><f n="Icon.icns" o="root" g="wheel" p="33188"/></f></f></f><f n="LICENSE.txt" o="root" g="wheel" p="33188"/><f n="package" o="root" g="wheel" p="16877"><f n="cultibox_apache.plist" o="root" g="wheel" p="33188"/><f n="cultibox_mysql.plist" o="root" g="wheel" p="33188"/><f n="InstallationCheck" o="root" g="wheel" p="33261"/><f n="postflight" o="root" g="wheel" p="33261"/><f n="postinstall" o="root" g="wheel" p="33261"/><f n="postinstall.new" o="root" g="wheel" p="33261"/><f n="postupgrade" o="root" g="wheel" p="33261"/><f n="preflight" o="root" g="wheel" p="33261"/><f n="preinstall" o="root" g="wheel" p="33261"/><f n="preupgrade" o="root" g="wheel" p="33261"/><f n="takecontrol.png" o="root" g="wheel" p="33188"/><f n="uninstall" o="root" g="wheel" p="33261"/><f n="VolumeCheck" o="root" g="wheel" p="33261"/></f><f n="run" o="root" g="wheel" p="16877"><f n="backup.sh" o="root" g="wheel" p="33261"/><f n="get_version.sh" o="root" g="wheel" p="33261"/><f n="load.sh" o="root" g="wheel" p="33261"/></f></f></pkg-contents>